{
"ri-lottery" : [
{"draw_date":"9/22/2020","ri_win4_eve":"6344","ri_win4_mid":"5769"},
{"draw_date":"9/23/2020","ri_win4_eve":"9112","ri_win4_mid":"6674"},
{"draw_date":"9/24/2020","ri_win4_eve":"5057","ri_win4_mid":"9274"},
{"draw_date":"9/25/2020","ri_win4_eve":"3009","ri_win4_mid":"3369"},
{"draw_date":"9/26/2020","ri_win4_eve":"1557","ri_win4_mid":"3618"},
{"draw_date":"9/27/2020","ri_win4_eve":"4720","ri_win4_mid":"3397"},
{"draw_date":"9/28/2020","ri_win4_eve":"8650","ri_win4_mid":"5179"},
{"draw_date":"9/29/2020","ri_win4_eve":"6846","ri_win4_mid":"6567"},
{"draw_date":"9/30/2020","ri_win4_eve":"1629","ri_win4_mid":"3950"},
{"draw_date":"10/1/2020","ri_win4_eve":"4733","ri_win4_mid":"8268"},
{"draw_date":"10/2/2020","ri_win4_eve":"3984","ri_win4_mid":"0277"},
{"draw_date":"10/3/2020","ri_win4_eve":"0951","ri_win4_mid":"6611"},
{"draw_date":"10/4/2020","ri_win4_eve":"0890","ri_win4_mid":"3190"},
{"draw_date":"10/5/2020","ri_win4_eve":"0197","ri_win4_mid":"7524"},
{"draw_date":"10/6/2020","ri_win4_eve":"2512","ri_win4_mid":"2650"},
{"draw_date":"10/7/2020","ri_win4_eve":"1744","ri_win4_mid":"0308"},
{"draw_date":"10/8/2020","ri_win4_eve":"3142","ri_win4_mid":"8673"},
{"draw_date":"10/9/2020","ri_win4_eve":"6703","ri_win4_mid":"3885"},
{"draw_date":"10/10/2020","ri_win4_eve":"5461","ri_win4_mid":"5813"},
{"draw_date":"10/11/2020","ri_win4_eve":"4903","ri_win4_mid":"0831"},
{"draw_date":"10/12/2020","ri_win4_eve":"3650","ri_win4_mid":"3135"},
{"draw_date":"10/13/2020","ri_win4_eve":"6265","ri_win4_mid":"6057"},
{"draw_date":"10/14/2020","ri_win4_eve":"0496","ri_win4_mid":"2644"},
{"draw_date":"10/15/2020","ri_win4_eve":"9108","ri_win4_mid":"3949"},
{"draw_date":"10/16/2020","ri_win4_eve":"7278","ri_win4_mid":"4476"},
{"draw_date":"10/17/2020","ri_win4_eve":"4091","ri_win4_mid":"5599"},
{"draw_date":"10/18/2020","ri_win4_eve":"5361","ri_win4_mid":"1821"},
{"draw_date":"10/19/2020","ri_win4_eve":"9265","ri_win4_mid":"3883"},
{"draw_date":"10/20/2020","ri_win4_eve":"3195","ri_win4_mid":"8375"},
{"draw_date":"10/21/2020","ri_win4_eve":"1865","ri_win4_mid":"2453"},
{"draw_date":"10/22/2020","ri_win4_eve":"7869","ri_win4_mid":"1171"},
{"draw_date":"10/23/2020","ri_win4_eve":"1277","ri_win4_mid":"3174"},
{"draw_date":"10/24/2020","ri_win4_eve":"9662","ri_win4_mid":"0476"},
{"draw_date":"10/25/2020","ri_win4_eve":"8115","ri_win4_mid":"1873"},
{"draw_date":"10/26/2020","ri_win4_eve":"2816","ri_win4_mid":"6813"},
{"draw_date":"10/27/2020","ri_win4_eve":"2945","ri_win4_mid":"7093"},
{"draw_date":"10/28/2020","ri_win4_eve":"6646","ri_win4_mid":"1219"},
{"draw_date":"10/29/2020","ri_win4_eve":"7417","ri_win4_mid":"3623"},
{"draw_date":"10/30/2020","ri_win4_eve":"4578","ri_win4_mid":"0539"},
{"draw_date":"10/31/2020","ri_win4_eve":"3905","ri_win4_mid":"7866"},
{"draw_date":"11/1/2020","ri_win4_eve":"2480","ri_win4_mid":"7291"},
{"draw_date":"11/2/2020","ri_win4_eve":"0616","ri_win4_mid":"3861"},
{"draw_date":"11/3/2020","ri_win4_eve":"4981","ri_win4_mid":"1720"},
{"draw_date":"11/4/2020","ri_win4_eve":"4778","ri_win4_mid":"5582"},
{"draw_date":"11/5/2020","ri_win4_eve":"5487","ri_win4_mid":"7547"},
{"draw_date":"11/6/2020","ri_win4_eve":"6409","ri_win4_mid":"1931"},
{"draw_date":"11/7/2020","ri_win4_eve":"8194","ri_win4_mid":"2880"},
{"draw_date":"11/8/2020","ri_win4_eve":"1449","ri_win4_mid":"9450"},
{"draw_date":"11/9/2020","ri_win4_eve":"5252","ri_win4_mid":"1807"},
{"draw_date":"11/10/2020","ri_win4_eve":"6238","ri_win4_mid":"0939"},
{"draw_date":"11/11/2020","ri_win4_eve":"5682","ri_win4_mid":"9965"},
{"draw_date":"11/12/2020","ri_win4_eve":"6757","ri_win4_mid":"4189"},
{"draw_date":"11/13/2020","ri_win4_eve":"0269","ri_win4_mid":"2178"},
{"draw_date":"11/14/2020","ri_win4_eve":"2467","ri_win4_mid":"2724"},
{"draw_date":"11/15/2020","ri_win4_eve":"7669","ri_win4_mid":"8205"},
{"draw_date":"11/16/2020","ri_win4_eve":"2145","ri_win4_mid":"2449"},
{"draw_date":"11/17/2020","ri_win4_eve":"3750","ri_win4_mid":"5251"},
{"draw_date":"11/18/2020","ri_win4_eve":"4659","ri_win4_mid":"5797"},
{"draw_date":"11/19/2020","ri_win4_eve":"1858","ri_win4_mid":"9491"},
{"draw_date":"11/20/2020","ri_win4_eve":"2811","ri_win4_mid":"7885"},
{"draw_date":"11/21/2020","ri_win4_eve":"9797","ri_win4_mid":"7619"},
{"draw_date":"11/22/2020","ri_win4_eve":"1721","ri_win4_mid":"8381"},
{"draw_date":"11/23/2020","ri_win4_eve":"3712","ri_win4_mid":"5011"},
{"draw_date":"11/24/2020","ri_win4_eve":"9882","ri_win4_mid":"6306"},
{"draw_date":"11/25/2020","ri_win4_eve":"3891","ri_win4_mid":"5274"},
{"draw_date":"11/26/2020","ri_win4_eve":"7819","ri_win4_mid":"9023"},
{"draw_date":"11/27/2020","ri_win4_eve":"8730","ri_win4_mid":"0315"},
{"draw_date":"11/28/2020","ri_win4_eve":"6758","ri_win4_mid":"1928"},
{"draw_date":"11/29/2020","ri_win4_eve":"3925","ri_win4_mid":"6879"},
{"draw_date":"11/30/2020","ri_win4_eve":"6366","ri_win4_mid":"9958"},
{"draw_date":"12/1/2020","ri_win4_eve":"5107","ri_win4_mid":"8234"},
{"draw_date":"12/2/2020","ri_win4_eve":"3908","ri_win4_mid":"7130"},
{"draw_date":"12/3/2020","ri_win4_eve":"2342","ri_win4_mid":"1689"},
{"draw_date":"12/4/2020","ri_win4_eve":"6080","ri_win4_mid":"0387"},
{"draw_date":"12/5/2020","ri_win4_eve":"8371","ri_win4_mid":"2832"},
{"draw_date":"12/6/2020","ri_win4_eve":"7885","ri_win4_mid":"5761"},
{"draw_date":"12/7/2020","ri_win4_eve":"4701","ri_win4_mid":"8531"},
{"draw_date":"12/8/2020","ri_win4_eve":"8767","ri_win4_mid":"9305"},
{"draw_date":"12/9/2020","ri_win4_eve":"4140","ri_win4_mid":"2420"},
{"draw_date":"12/10/2020","ri_win4_eve":"5609","ri_win4_mid":"8365"},
{"draw_date":"12/11/2020","ri_win4_eve":"6458","ri_win4_mid":"4169"},
{"draw_date":"12/12/2020","ri_win4_eve":"3146","ri_win4_mid":"4758"},
{"draw_date":"12/13/2020","ri_win4_eve":"9406","ri_win4_mid":"4489"},
{"draw_date":"12/14/2020","ri_win4_eve":"0050","ri_win4_mid":"9807"},
{"draw_date":"12/15/2020","ri_win4_eve":"0598","ri_win4_mid":"9581"},
{"draw_date":"12/16/2020","ri_win4_eve":"6857","ri_win4_mid":"8909"},
{"draw_date":"12/17/2020","ri_win4_eve":"5561","ri_win4_mid":"7346"},
{"draw_date":"12/18/2020","ri_win4_eve":"9094","ri_win4_mid":"0699"},
{"draw_date":"12/19/2020","ri_win4_eve":"8666","ri_win4_mid":"2646"},
{"draw_date":"12/20/2020","ri_win4_eve":"5448","ri_win4_mid":"1840"},
{"draw_date":"12/21/2020","ri_win4_eve":"2387","ri_win4_mid":"1077"},
{"draw_date":"12/22/2020","ri_win4_eve":"0118","ri_win4_mid":"2764"},
{"draw_date":"12/23/2020","ri_win4_eve":"3997","ri_win4_mid":"6891"},
{"draw_date":"12/24/2020","ri_win4_eve":"5380","ri_win4_mid":"8912"},
{"draw_date":"12/25/2020","ri_win4_eve":"9502","ri_win4_mid":"1027"},
{"draw_date":"12/26/2020","ri_win4_eve":"0094","ri_win4_mid":"4269"},
{"draw_date":"12/27/2020","ri_win4_eve":"5165","ri_win4_mid":"8800"},
{"draw_date":"12/28/2020","ri_win4_eve":"4124","ri_win4_mid":"0580"},
{"draw_date":"12/29/2020","ri_win4_eve":"9439","ri_win4_mid":"2370"},
{"draw_date":"12/30/2020","ri_win4_eve":"6997","ri_win4_mid":"8139"},
{"draw_date":"12/31/2020","ri_win4_eve":"8832","ri_win4_mid":"9413"},
{"draw_date":"1/1/2021","ri_win4_eve":"2359","ri_win4_mid":"8007"},
{"draw_date":"1/2/2021","ri_win4_eve":"2241","ri_win4_mid":"0048"},
{"draw_date":"1/3/2021","ri_win4_eve":"7029","ri_win4_mid":"2084"},
{"draw_date":"1/4/2021","ri_win4_eve":"6636","ri_win4_mid":"7792"},
{"draw_date":"1/5/2021","ri_win4_eve":"0545","ri_win4_mid":"2615"},
{"draw_date":"1/6/2021","ri_win4_eve":"4656","ri_win4_mid":"9120"},
{"draw_date":"1/7/2021","ri_win4_eve":"5774","ri_win4_mid":"1011"},
{"draw_date":"1/8/2021","ri_win4_eve":"9219","ri_win4_mid":"7320"},
{"draw_date":"1/9/2021","ri_win4_eve":"1423","ri_win4_mid":"4437"},
{"draw_date":"1/10/2021","ri_win4_eve":"2955","ri_win4_mid":"8991"},
{"draw_date":"1/11/2021","ri_win4_eve":"9558","ri_win4_mid":"4922"},
{"draw_date":"1/12/2021","ri_win4_eve":"0482","ri_win4_mid":"4971"},
{"draw_date":"1/13/2021","ri_win4_eve":"2302","ri_win4_mid":"1483"},
{"draw_date":"1/14/2021","ri_win4_eve":"9481","ri_win4_mid":"5177"},
{"draw_date":"1/15/2021","ri_win4_eve":"4843","ri_win4_mid":"5108"},
{"draw_date":"1/16/2021","ri_win4_eve":"5302","ri_win4_mid":"4760"},
{"draw_date":"1/17/2021","ri_win4_eve":"8073","ri_win4_mid":"8540"},
{"draw_date":"1/18/2021","ri_win4_eve":"1008","ri_win4_mid":"0614"},
{"draw_date":"1/19/2021","ri_win4_eve":"4743","ri_win4_mid":"4517"},
{"draw_date":"1/20/2021","ri_win4_eve":"0379","ri_win4_mid":"5400"},
{"draw_date":"1/21/2021","ri_win4_eve":"4865","ri_win4_mid":"8422"},
{"draw_date":"1/22/2021","ri_win4_eve":"8206","ri_win4_mid":"7581"},
{"draw_date":"1/23/2021","ri_win4_eve":"9240","ri_win4_mid":"6991"},
{"draw_date":"1/24/2021","ri_win4_eve":"6048","ri_win4_mid":"5048"},
{"draw_date":"1/25/2021","ri_win4_eve":"2913","ri_win4_mid":"6724"},
{"draw_date":"1/26/2021","ri_win4_eve":"3122","ri_win4_mid":"3760"},
{"draw_date":"1/27/2021","ri_win4_eve":"4324","ri_win4_mid":"7869"},
{"draw_date":"1/28/2021","ri_win4_eve":"6982","ri_win4_mid":"1443"},
{"draw_date":"1/29/2021","ri_win4_eve":"6222","ri_win4_mid":"9378"},
{"draw_date":"1/30/2021","ri_win4_eve":"5762","ri_win4_mid":"5683"},
{"draw_date":"1/31/2021","ri_win4_eve":"4361","ri_win4_mid":"1019"},
{"draw_date":"2/1/2021","ri_win4_eve":"0297","ri_win4_mid":"6611"},
{"draw_date":"2/2/2021","ri_win4_eve":"6286","ri_win4_mid":"7450"},
{"draw_date":"2/3/2021","ri_win4_eve":"6261","ri_win4_mid":"4397"},
{"draw_date":"2/4/2021","ri_win4_eve":"6693","ri_win4_mid":"5151"},
{"draw_date":"2/5/2021","ri_win4_eve":"9898","ri_win4_mid":"9168"},
{"draw_date":"2/6/2021","ri_win4_eve":"7272","ri_win4_mid":"3197"},
{"draw_date":"2/7/2021","ri_win4_eve":"3218","ri_win4_mid":"3318"},
{"draw_date":"2/8/2021","ri_win4_eve":"7835","ri_win4_mid":"7230"},
{"draw_date":"2/9/2021","ri_win4_eve":"9335","ri_win4_mid":"2232"},
{"draw_date":"2/10/2021","ri_win4_eve":"6912","ri_win4_mid":"9848"},
{"draw_date":"2/11/2021","ri_win4_eve":"7389","ri_win4_mid":"1791"},
{"draw_date":"2/12/2021","ri_win4_eve":"6410","ri_win4_mid":"8378"},
{"draw_date":"2/13/2021","ri_win4_eve":"1756","ri_win4_mid":"2800"},
{"draw_date":"2/14/2021","ri_win4_eve":"6271","ri_win4_mid":"9714"},
{"draw_date":"2/15/2021","ri_win4_eve":"6536","ri_win4_mid":"1976"},
{"draw_date":"2/16/2021","ri_win4_eve":"5978","ri_win4_mid":"7748"},
{"draw_date":"2/17/2021","ri_win4_eve":"8817","ri_win4_mid":"9895"},
{"draw_date":"2/18/2021","ri_win4_eve":"0203","ri_win4_mid":"5774"},
{"draw_date":"2/19/2021","ri_win4_eve":"0157","ri_win4_mid":"1173"},
{"draw_date":"2/20/2021","ri_win4_eve":"5886","ri_win4_mid":"8118"},
{"draw_date":"2/21/2021","ri_win4_eve":"3618","ri_win4_mid":"1243"},
{"draw_date":"2/22/2021","ri_win4_eve":"4553","ri_win4_mid":"2126"},
{"draw_date":"2/23/2021","ri_win4_eve":"0293","ri_win4_mid":"3362"},
{"draw_date":"2/24/2021","ri_win4_eve":"3475","ri_win4_mid":"1524"},
{"draw_date":"2/25/2021","ri_win4_eve":"7932","ri_win4_mid":"9800"},
{"draw_date":"2/26/2021","ri_win4_eve":"1562","ri_win4_mid":"7860"},
{"draw_date":"2/27/2021","ri_win4_eve":"8026","ri_win4_mid":"8359"},
{"draw_date":"2/28/2021","ri_win4_eve":"7139","ri_win4_mid":"0498"},
{"draw_date":"3/1/2021","ri_win4_eve":"8188","ri_win4_mid":"1992"},
{"draw_date":"3/2/2021","ri_win4_eve":"2606","ri_win4_mid":"3642"},
{"draw_date":"3/3/2021","ri_win4_eve":"5975","ri_win4_mid":"0339"},
{"draw_date":"3/4/2021","ri_win4_eve":"0214","ri_win4_mid":"2277"},
{"draw_date":"3/5/2021","ri_win4_eve":"7898","ri_win4_mid":"4180"},
{"draw_date":"3/6/2021","ri_win4_eve":"4387","ri_win4_mid":"3537"},
{"draw_date":"3/7/2021","ri_win4_eve":"3294","ri_win4_mid":"9559"},
{"draw_date":"3/8/2021","ri_win4_eve":"1071","ri_win4_mid":"5160"},
{"draw_date":"3/9/2021","ri_win4_eve":"7827","ri_win4_mid":"7929"},
{"draw_date":"3/10/2021","ri_win4_eve":"4976","ri_win4_mid":"5045"},
{"draw_date":"3/11/2021","ri_win4_eve":"1385","ri_win4_mid":"5315"},
{"draw_date":"3/12/2021","ri_win4_eve":"9849","ri_win4_mid":"3966"},
{"draw_date":"3/13/2021","ri_win4_eve":"4405","ri_win4_mid":"3452"},
{"draw_date":"3/14/2021","ri_win4_eve":"2445","ri_win4_mid":"7227"},
{"draw_date":"3/15/2021","ri_win4_eve":"7143","ri_win4_mid":"9763"},
{"draw_date":"3/16/2021","ri_win4_eve":"5776","ri_win4_mid":"9638"},
{"draw_date":"3/17/2021","ri_win4_eve":"0301","ri_win4_mid":"9648"},
{"draw_date":"3/18/2021","ri_win4_eve":"1898","ri_win4_mid":"2256"},
{"draw_date":"3/19/2021","ri_win4_eve":"8298","ri_win4_mid":"2807"},
{"draw_date":"3/20/2021","ri_win4_eve":"9109","ri_win4_mid":"1619"},
{"draw_date":"3/21/2021","ri_win4_eve":"8483","ri_win4_mid":"6052"},
{"draw_date":"3/22/2021","ri_win4_eve":"9412","ri_win4_mid":"6093"},
{"draw_date":"3/23/2021","ri_win4_eve":"4552","ri_win4_mid":"1876"},
{"draw_date":"3/24/2021","ri_win4_eve":"3905","ri_win4_mid":"1424"},
{"draw_date":"3/25/2021","ri_win4_eve":"7981","ri_win4_mid":"7040"},
{"draw_date":"3/26/2021","ri_win4_eve":"9417","ri_win4_mid":"1601"},
{"draw_date":"3/27/2021","ri_win4_eve":"8561","ri_win4_mid":"6763"},
{"draw_date":"3/28/2021","ri_win4_eve":"4497","ri_win4_mid":"3468"},
{"draw_date":"3/29/2021","ri_win4_eve":"1203","ri_win4_mid":"1146"},
{"draw_date":"3/30/2021","ri_win4_eve":"2723","ri_win4_mid":"6181"},
{"draw_date":"3/31/2021","ri_win4_eve":"8605","ri_win4_mid":"8701"},
{"draw_date":"4/1/2021","ri_win4_eve":"9236","ri_win4_mid":"7389"},
{"draw_date":"4/2/2021","ri_win4_eve":"5440","ri_win4_mid":"5059"},
{"draw_date":"4/3/2021","ri_win4_eve":"8072","ri_win4_mid":"5411"},
{"draw_date":"4/4/2021","ri_win4_eve":"2698","ri_win4_mid":"0120"},
{"draw_date":"4/5/2021","ri_win4_eve":"6986","ri_win4_mid":"6918"},
{"draw_date":"4/6/2021","ri_win4_eve":"2960","ri_win4_mid":"9006"},
{"draw_date":"4/7/2021","ri_win4_eve":"3964","ri_win4_mid":"9934"},
{"draw_date":"4/8/2021","ri_win4_eve":"9312","ri_win4_mid":"5230"},
{"draw_date":"4/9/2021","ri_win4_eve":"9840","ri_win4_mid":"4547"},
{"draw_date":"4/10/2021","ri_win4_eve":"4280","ri_win4_mid":"7365"},
{"draw_date":"4/11/2021","ri_win4_eve":"7111","ri_win4_mid":"4321"},
{"draw_date":"4/12/2021","ri_win4_eve":"6731","ri_win4_mid":"2378"},
{"draw_date":"4/13/2021","ri_win4_eve":"1447","ri_win4_mid":"0281"},
{"draw_date":"4/14/2021","ri_win4_eve":"2720","ri_win4_mid":"5091"},
{"draw_date":"4/15/2021","ri_win4_eve":"2102","ri_win4_mid":"2635"},
{"draw_date":"4/16/2021","ri_win4_eve":"8085","ri_win4_mid":"1895"},
{"draw_date":"4/17/2021","ri_win4_eve":"5613","ri_win4_mid":"2923"},
{"draw_date":"4/18/2021","ri_win4_eve":"5678","ri_win4_mid":"4541"},
{"draw_date":"4/19/2021","ri_win4_eve":"0318","ri_win4_mid":"7720"},
{"draw_date":"4/20/2021","ri_win4_eve":"2214","ri_win4_mid":"3568"},
{"draw_date":"4/21/2021","ri_win4_eve":"3449","ri_win4_mid":"5474"},
{"draw_date":"4/22/2021","ri_win4_eve":"4624","ri_win4_mid":"3611"},
{"draw_date":"4/23/2021","ri_win4_eve":"3488","ri_win4_mid":"0338"},
{"draw_date":"4/24/2021","ri_win4_eve":"7314","ri_win4_mid":"7296"},
{"draw_date":"4/25/2021","ri_win4_eve":"6935","ri_win4_mid":"3074"},
{"draw_date":"4/26/2021","ri_win4_eve":"1326","ri_win4_mid":"4141"},
{"draw_date":"4/27/2021","ri_win4_eve":"2361","ri_win4_mid":"2627"},
{"draw_date":"4/28/2021","ri_win4_eve":"2927","ri_win4_mid":"5691"},
{"draw_date":"4/29/2021","ri_win4_eve":"6284","ri_win4_mid":"0876"},
{"draw_date":"4/30/2021","ri_win4_eve":"0749","ri_win4_mid":"7271"},
{"draw_date":"5/1/2021","ri_win4_eve":"6707","ri_win4_mid":"2065"},
{"draw_date":"5/2/2021","ri_win4_eve":"2712","ri_win4_mid":"7343"},
{"draw_date":"5/3/2021","ri_win4_eve":"5231","ri_win4_mid":"2128"},
{"draw_date":"5/4/2021","ri_win4_eve":"2990","ri_win4_mid":"2731"},
{"draw_date":"5/5/2021","ri_win4_eve":"1661","ri_win4_mid":"0109"},
{"draw_date":"5/6/2021","ri_win4_eve":"3287","ri_win4_mid":"3636"},
{"draw_date":"5/7/2021","ri_win4_eve":"8750","ri_win4_mid":"6611"},
{"draw_date":"5/8/2021","ri_win4_eve":"1089","ri_win4_mid":"3573"},
{"draw_date":"5/9/2021","ri_win4_eve":"5063","ri_win4_mid":"0260"},
{"draw_date":"5/10/2021","ri_win4_eve":"3921","ri_win4_mid":"1265"},
{"draw_date":"5/11/2021","ri_win4_eve":"7129","ri_win4_mid":"9933"},
{"draw_date":"5/12/2021","ri_win4_eve":"6153","ri_win4_mid":"3743"},
{"draw_date":"5/13/2021","ri_win4_eve":"8971","ri_win4_mid":"7604"},
{"draw_date":"5/14/2021","ri_win4_eve":"1230","ri_win4_mid":"4253"},
{"draw_date":"5/15/2021","ri_win4_eve":"8021","ri_win4_mid":"1200"},
{"draw_date":"5/16/2021","ri_win4_eve":"6179","ri_win4_mid":"8027"},
{"draw_date":"5/17/2021","ri_win4_eve":"3915","ri_win4_mid":"3660"},
{"draw_date":"5/18/2021","ri_win4_eve":"9200","ri_win4_mid":"0722"},
{"draw_date":"5/19/2021","ri_win4_eve":"4518","ri_win4_mid":"6152"},
{"draw_date":"5/20/2021","ri_win4_eve":"9799","ri_win4_mid":"6439"},
{"draw_date":"5/21/2021","ri_win4_eve":"1015","ri_win4_mid":"6283"},
{"draw_date":"5/22/2021","ri_win4_eve":"5511","ri_win4_mid":"9922"},
{"draw_date":"5/23/2021","ri_win4_eve":"0601","ri_win4_mid":"6911"},
{"draw_date":"5/24/2021","ri_win4_eve":"5034","ri_win4_mid":"7223"},
{"draw_date":"5/25/2021","ri_win4_eve":"7632","ri_win4_mid":"5422"},
{"draw_date":"5/26/2021","ri_win4_eve":"6816","ri_win4_mid":"1285"},
{"draw_date":"5/27/2021","ri_win4_eve":"8551","ri_win4_mid":"5858"},
{"draw_date":"5/28/2021","ri_win4_eve":"6997","ri_win4_mid":"6529"},
{"draw_date":"5/29/2021","ri_win4_eve":"5467","ri_win4_mid":"2866"},
{"draw_date":"5/30/2021","ri_win4_eve":"9430","ri_win4_mid":"4268"},
{"draw_date":"5/31/2021","ri_win4_eve":"9960","ri_win4_mid":"1121"},
{"draw_date":"6/1/2021","ri_win4_eve":"0852","ri_win4_mid":"9443"},
{"draw_date":"6/2/2021","ri_win4_eve":"7521","ri_win4_mid":"3299"},
{"draw_date":"6/3/2021","ri_win4_eve":"3841","ri_win4_mid":"3501"},
{"draw_date":"6/4/2021","ri_win4_eve":"4216","ri_win4_mid":"5040"},
{"draw_date":"6/5/2021","ri_win4_eve":"2589","ri_win4_mid":"4549"},
{"draw_date":"6/6/2021","ri_win4_eve":"0700","ri_win4_mid":"8950"},
{"draw_date":"6/7/2021","ri_win4_eve":"7654","ri_win4_mid":"8095"},
{"draw_date":"6/8/2021","ri_win4_eve":"2742","ri_win4_mid":"7404"},
{"draw_date":"6/9/2021","ri_win4_eve":"4883","ri_win4_mid":"0687"},
{"draw_date":"6/10/2021","ri_win4_eve":"8970","ri_win4_mid":"3356"},
{"draw_date":"6/11/2021","ri_win4_eve":"2489","ri_win4_mid":"5763"},
{"draw_date":"6/12/2021","ri_win4_eve":"1278","ri_win4_mid":"9498"},
{"draw_date":"6/13/2021","ri_win4_eve":"0850","ri_win4_mid":"3434"},
{"draw_date":"6/14/2021","ri_win4_eve":"0492","ri_win4_mid":"4728"},
{"draw_date":"6/15/2021","ri_win4_eve":"5502","ri_win4_mid":"5572"},
{"draw_date":"6/16/2021","ri_win4_eve":"4112","ri_win4_mid":"1351"},
{"draw_date":"6/17/2021","ri_win4_eve":"0965","ri_win4_mid":"8290"},
{"draw_date":"6/18/2021","ri_win4_eve":"0014","ri_win4_mid":"4201"},
{"draw_date":"6/19/2021","ri_win4_eve":"1686","ri_win4_mid":"6919"},
{"draw_date":"6/20/2021","ri_win4_eve":"5530","ri_win4_mid":"9936"},
{"draw_date":"6/21/2021","ri_win4_eve":"5756","ri_win4_mid":"6244"},
{"draw_date":"6/22/2021","ri_win4_eve":"4058","ri_win4_mid":"7031"},
{"draw_date":"6/23/2021","ri_win4_eve":"1002","ri_win4_mid":"0154"},
{"draw_date":"6/24/2021","ri_win4_eve":"8181","ri_win4_mid":"7985"},
{"draw_date":"6/25/2021","ri_win4_eve":"9653","ri_win4_mid":"5274"},
{"draw_date":"6/26/2021","ri_win4_eve":"8984","ri_win4_mid":"6248"},
{"draw_date":"6/27/2021","ri_win4_eve":"1089","ri_win4_mid":"0424"},
{"draw_date":"6/28/2021","ri_win4_eve":"4964","ri_win4_mid":"9805"},
{"draw_date":"6/29/2021","ri_win4_eve":"8565","ri_win4_mid":"9150"},
{"draw_date":"6/30/2021","ri_win4_eve":"1427","ri_win4_mid":"1750"},
{"draw_date":"7/1/2021","ri_win4_eve":"8581","ri_win4_mid":"0377"},
{"draw_date":"7/2/2021","ri_win4_eve":"6371","ri_win4_mid":"7605"},
{"draw_date":"7/3/2021","ri_win4_eve":"1967","ri_win4_mid":"5676"},
{"draw_date":"7/4/2021","ri_win4_eve":"5130","ri_win4_mid":"0637"},
{"draw_date":"7/5/2021","ri_win4_eve":"8553","ri_win4_mid":"9462"},
{"draw_date":"7/6/2021","ri_win4_eve":"9035","ri_win4_mid":"9597"},
{"draw_date":"7/7/2021","ri_win4_eve":"9248","ri_win4_mid":"1549"},
{"draw_date":"7/8/2021","ri_win4_eve":"0522","ri_win4_mid":"3714"},
{"draw_date":"7/9/2021","ri_win4_eve":"4710","ri_win4_mid":"2095"},
{"draw_date":"7/10/2021","ri_win4_eve":"9445","ri_win4_mid":"3924"},
{"draw_date":"7/11/2021","ri_win4_eve":"4408","ri_win4_mid":"3079"},
{"draw_date":"7/12/2021","ri_win4_eve":"3352","ri_win4_mid":"7464"},
{"draw_date":"7/13/2021","ri_win4_eve":"6309","ri_win4_mid":"8668"},
{"draw_date":"7/14/2021","ri_win4_eve":"4097","ri_win4_mid":"1068"},
{"draw_date":"7/15/2021","ri_win4_eve":"1511","ri_win4_mid":"6131"},
{"draw_date":"7/16/2021","ri_win4_eve":"2558","ri_win4_mid":"6943"},
{"draw_date":"7/17/2021","ri_win4_eve":"1221","ri_win4_mid":"0756"},
{"draw_date":"7/18/2021","ri_win4_eve":"0099","ri_win4_mid":"6701"},
{"draw_date":"7/19/2021","ri_win4_eve":"3605","ri_win4_mid":"5215"},
{"draw_date":"7/20/2021","ri_win4_eve":"4385","ri_win4_mid":"3918"},
{"draw_date":"7/21/2021","ri_win4_eve":"5649","ri_win4_mid":"5282"},
{"draw_date":"7/22/2021","ri_win4_eve":"9305","ri_win4_mid":"7368"},
{"draw_date":"7/23/2021","ri_win4_eve":"3394","ri_win4_mid":"5409"},
{"draw_date":"7/24/2021","ri_win4_eve":"7702","ri_win4_mid":"6002"},
{"draw_date":"7/25/2021","ri_win4_eve":"8971","ri_win4_mid":"3601"},
{"draw_date":"7/26/2021","ri_win4_eve":"4242","ri_win4_mid":"5022"},
{"draw_date":"7/27/2021","ri_win4_eve":"4490","ri_win4_mid":"1954"},
{"draw_date":"7/28/2021","ri_win4_eve":"7911","ri_win4_mid":"5593"},
{"draw_date":"7/29/2021","ri_win4_eve":"1928","ri_win4_mid":"5471"},
{"draw_date":"7/30/2021","ri_win4_eve":"2055","ri_win4_mid":"6598"},
{"draw_date":"7/31/2021","ri_win4_eve":"5305","ri_win4_mid":"4638"},
{"draw_date":"8/1/2021","ri_win4_eve":"6400","ri_win4_mid":"1936"},
{"draw_date":"8/2/2021","ri_win4_eve":"2011","ri_win4_mid":"8208"},
{"draw_date":"8/3/2021","ri_win4_eve":"5442","ri_win4_mid":"8161"},
{"draw_date":"8/4/2021","ri_win4_eve":"3357","ri_win4_mid":"2728"},
{"draw_date":"8/5/2021","ri_win4_eve":"5320","ri_win4_mid":"3875"},
{"draw_date":"8/6/2021","ri_win4_eve":"1497","ri_win4_mid":"0828"},
{"draw_date":"8/7/2021","ri_win4_eve":"6456","ri_win4_mid":"3376"},
{"draw_date":"8/8/2021","ri_win4_eve":"8034","ri_win4_mid":"6545"},
{"draw_date":"8/9/2021","ri_win4_eve":"9606","ri_win4_mid":"9402"},
{"draw_date":"8/10/2021","ri_win4_eve":"7179","ri_win4_mid":"4910"},
{"draw_date":"8/11/2021","ri_win4_eve":"8905","ri_win4_mid":"0767"},
{"draw_date":"8/12/2021","ri_win4_eve":"5461","ri_win4_mid":"2941"},
{"draw_date":"8/13/2021","ri_win4_eve":"6255","ri_win4_mid":"2268"},
{"draw_date":"8/14/2021","ri_win4_eve":"7506","ri_win4_mid":"8387"},
{"draw_date":"8/15/2021","ri_win4_eve":"2085","ri_win4_mid":"5834"},
{"draw_date":"8/16/2021","ri_win4_eve":"4888","ri_win4_mid":"7183"},
{"draw_date":"8/17/2021","ri_win4_eve":"5506","ri_win4_mid":"5271"},
{"draw_date":"8/18/2021","ri_win4_eve":"8273","ri_win4_mid":"6380"},
{"draw_date":"8/19/2021","ri_win4_eve":"1166","ri_win4_mid":"8185"},
{"draw_date":"8/20/2021","ri_win4_eve":"6734","ri_win4_mid":"8094"},
{"draw_date":"8/21/2021","ri_win4_eve":"3409","ri_win4_mid":"9663"},
{"draw_date":"8/22/2021","ri_win4_eve":"0668","ri_win4_mid":"8364"},
{"draw_date":"8/23/2021","ri_win4_eve":"1134","ri_win4_mid":"8375"},
{"draw_date":"8/24/2021","ri_win4_eve":"0756","ri_win4_mid":"8260"},
{"draw_date":"8/25/2021","ri_win4_eve":"5497","ri_win4_mid":"2690"},
{"draw_date":"8/26/2021","ri_win4_eve":"2053","ri_win4_mid":"3735"},
{"draw_date":"8/27/2021","ri_win4_eve":"3635","ri_win4_mid":"2430"},
{"draw_date":"8/28/2021","ri_win4_eve":"5667","ri_win4_mid":"3338"},
{"draw_date":"8/29/2021","ri_win4_eve":"9468","ri_win4_mid":"7920"},
{"draw_date":"8/30/2021","ri_win4_eve":"1718","ri_win4_mid":"6269"},
{"draw_date":"8/31/2021","ri_win4_eve":"9036","ri_win4_mid":"2027"},
{"draw_date":"9/1/2021","ri_win4_eve":"6286","ri_win4_mid":"9784"},
{"draw_date":"9/2/2021","ri_win4_eve":"6253","ri_win4_mid":"8792"},
{"draw_date":"9/3/2021","ri_win4_eve":"8787","ri_win4_mid":"6322"},
{"draw_date":"9/4/2021","ri_win4_eve":"9335","ri_win4_mid":"9304"},
{"draw_date":"9/5/2021","ri_win4_eve":"0370","ri_win4_mid":"4322"},
{"draw_date":"9/6/2021","ri_win4_eve":"6643","ri_win4_mid":"8675"},
{"draw_date":"9/7/2021","ri_win4_eve":"8123","ri_win4_mid":"7156"},
{"draw_date":"9/8/2021","ri_win4_eve":"7545","ri_win4_mid":"5179"},
{"draw_date":"9/9/2021","ri_win4_eve":"4547","ri_win4_mid":"7721"},
{"draw_date":"9/10/2021","ri_win4_eve":"2349","ri_win4_mid":"6705"},
{"draw_date":"9/11/2021","ri_win4_eve":"8547","ri_win4_mid":"4203"},
{"draw_date":"9/12/2021","ri_win4_eve":"5029","ri_win4_mid":"4745"},
{"draw_date":"9/13/2021","ri_win4_eve":"7799","ri_win4_mid":"6461"},
{"draw_date":"9/14/2021","ri_win4_eve":"9294","ri_win4_mid":"7742"},
{"draw_date":"9/15/2021","ri_win4_eve":"2366","ri_win4_mid":"1891"},
{"draw_date":"9/16/2021","ri_win4_eve":"6432","ri_win4_mid":"6066"},
{"draw_date":"9/17/2021","ri_win4_eve":"9434","ri_win4_mid":"0426"},
{"draw_date":"9/18/2021","ri_win4_eve":"5044","ri_win4_mid":"9646"},
{"draw_date":"9/19/2021","ri_win4_eve":"4129","ri_win4_mid":"2500"},
{"draw_date":"9/20/2021","ri_win4_eve":"6588","ri_win4_mid":"2827"},
{"draw_date":"9/21/2021","ri_win4_eve":"7436","ri_win4_mid":"9336"},
{"draw_date":"9/22/2021","ri_win4_eve":"7916","ri_win4_mid":"9154"},
{"draw_date":"9/23/2021","ri_win4_eve":"6267","ri_win4_mid":"5630"},
{"draw_date":"9/24/2021","ri_win4_eve":"9733","ri_win4_mid":"5841"},
{"draw_date":"9/25/2021","ri_win4_eve":"2942","ri_win4_mid":"5582"},
{"draw_date":"9/26/2021","ri_win4_eve":"4703","ri_win4_mid":"6891"},
{"draw_date":"9/27/2021","ri_win4_eve":"2772","ri_win4_mid":"0420"},
{"draw_date":"9/28/2021","ri_win4_eve":"3492","ri_win4_mid":"5439"},
{"draw_date":"9/29/2021","ri_win4_eve":"3705","ri_win4_mid":"3658"},
{"draw_date":"9/30/2021","ri_win4_eve":"8505","ri_win4_mid":"9758"}
]
}
